langchain_openrouter/README.md
langchain_openrouter/__init__.py
langchain_openrouter/chat_models/base.py
langchain_openrouter_chat-0.0.1.dist-info/METADATA
langchain_openrouter_chat-0.0.1.dist-info/WHEEL
langchain_openrouter_chat-0.0.1.dist-info/RECORD
